tcrf/__init__.py
tcrf/crf.py
tcrf/crf_utils.py
tcrf/main.py
tcrf/models.py
tcrf/trainers.py
tcrf/utils.py
tcrf-0.0.1.dist-info/LICENSE
tcrf-0.0.1.dist-info/METADATA
tcrf-0.0.1.dist-info/WHEEL
tcrf-0.0.1.dist-info/top_level.txt
tcrf-0.0.1.dist-info/RECORD
